DataPrepKitH/__init__.py
DataPrepKitH-0.1.0.dist-info/LICENCE.txt
DataPrepKitH-0.1.0.dist-info/METADATA
DataPrepKitH-0.1.0.dist-info/WHEEL
DataPrepKitH-0.1.0.dist-info/top_level.txt
DataPrepKitH-0.1.0.dist-info/RECORD
